mmyolo/__init__.py
mmyolo/registry.py
mmyolo/version.py
mmyolo/.mim/model-index.yml
mmyolo/.mim/configs/_base_/default_runtime.py
mmyolo/.mim/configs/_base_/det_p5_tta.py
mmyolo/.mim/configs/_base_/pose/coco.py
mmyolo/.mim/configs/deploy/base_dynamic.py
mmyolo/.mim/configs/deploy/base_static.py
mmyolo/.mim/configs/deploy/detection_onnxruntime_dynamic.py
mmyolo/.mim/configs/deploy/detection_onnxruntime_static.py
mmyolo/.mim/configs/deploy/detection_rknn-fp16_static-320x320.py
mmyolo/.mim/configs/deploy/detection_rknn-int8_static-320x320.py
mmyolo/.mim/configs/deploy/detection_tensorrt-fp16_dynamic-192x192-960x960.py
mmyolo/.mim/configs/deploy/detection_tensorrt-fp16_dynamic-64x64-1344x1344.py
mmyolo/.mim/configs/deploy/detection_tensorrt-fp16_static-640x640.py
mmyolo/.mim/configs/deploy/detection_tensorrt-int8_dynamic-192x192-960x960.py
mmyolo/.mim/configs/deploy/detection_tensorrt-int8_static-640x640.py
mmyolo/.mim/configs/deploy/detection_tensorrt_dynamic-192x192-960x960.py
mmyolo/.mim/configs/deploy/detection_tensorrt_static-640x640.py
mmyolo/.mim/configs/deploy/model/yolov5_s-static.py
mmyolo/.mim/configs/deploy/model/yolov6_s-static.py
mmyolo/.mim/configs/ppyoloe/metafile.yml
mmyolo/.mim/configs/ppyoloe/ppyoloe_l_fast_8xb20-300e_coco.py
mmyolo/.mim/configs/ppyoloe/ppyoloe_m_fast_8xb28-300e_coco.py
mmyolo/.mim/configs/ppyoloe/ppyoloe_plus_l_fast_8xb8-80e_coco.py
mmyolo/.mim/configs/ppyoloe/ppyoloe_plus_m_fast_8xb8-80e_coco.py
mmyolo/.mim/configs/ppyoloe/ppyoloe_plus_s_fast_1xb12-40e_cat.py
mmyolo/.mim/configs/ppyoloe/ppyoloe_plus_s_fast_8xb8-80e_coco.py
mmyolo/.mim/configs/ppyoloe/ppyoloe_plus_x_fast_8xb8-80e_coco.py
mmyolo/.mim/configs/ppyoloe/ppyoloe_s_fast_8xb32-300e_coco.py
mmyolo/.mim/configs/ppyoloe/ppyoloe_s_fast_8xb32-400e_coco.py
mmyolo/.mim/configs/ppyoloe/ppyoloe_x_fast_8xb16-300e_coco.py
mmyolo/.mim/configs/razor/subnets/rtmdet_tiny_ofa_lat31_syncbn_16xb16-300e_coco.py
visaionmmyolo_118_202511031407-0.6.0.dist-info/licenses/LICENSE
visaionmmyolo_118_202511031407-0.6.0.dist-info/METADATA
visaionmmyolo_118_202511031407-0.6.0.dist-info/WHEEL
visaionmmyolo_118_202511031407-0.6.0.dist-info/top_level.txt
visaionmmyolo_118_202511031407-0.6.0.dist-info/RECORD
